bmx/__init__.py
bmx/core.py
bmx/htmltags.py
bmx-0.0.3.dist-info/LICENSE
bmx-0.0.3.dist-info/WHEEL
bmx-0.0.3.dist-info/METADATA
bmx-0.0.3.dist-info/RECORD
