Metadata-Version: 2.1
Name: bmx
Version: 0.0.3
Summary: Basic Markup eXpressions
Home-page: https://github.com/stuartpullinger/bmx
License: MPL-2.0
Keywords: html,xml,templating,markup
Author: Stuart Pullinger
Author-email: stuartpullinger@gmail.com
Requires-Python: >=3.6.1,<4.0.0
Classifier: Development Status :: 3 - Alpha
Classifier: Intended Audience :: Developers
Classifier: License :: OSI Approved
Classifier: Operating System :: OS Independent
Classifier: Programming Language :: Python :: 3
Classifier: Programming Language :: Python :: 3.7
Classifier: Programming Language :: Python :: 3.8
Classifier: Programming Language :: Python :: 3.9
Classifier: Topic :: Internet :: WWW/HTTP :: Dynamic Content
Classifier: Topic :: Software Development :: Libraries :: Python Modules
Classifier: Topic :: Text Processing :: Markup :: HTML
Classifier: Topic :: Text Processing :: Markup :: XML
Requires-Dist: MarkupSafe (>=1.1.1,<2.0.0)
Requires-Dist: singledispatchmethod; python_version < "3.8"
Project-URL: Repository, https://github.com/stuartpullinger/bmx
